Eliza/__init__.py
Eliza/main.py
elizaquant-0.1.dist-info/METADATA
elizaquant-0.1.dist-info/WHEEL
elizaquant-0.1.dist-info/top_level.txt
elizaquant-0.1.dist-info/RECORD
